TPI/TPI-Codigo/UARTComp/FIFO.v
module FIFO(
    input wire wr,            //señal de escritura
    input wire rd,            //señal de lectura
    input [7:0] w_data,       //dato de escritura
    output reg [7:0] r_data,  //dato de lectura
    output wire full,         //bandera de llena
    output wire empty         //bandera de vacia
);

//punteros de escritura y lectura
//--un bit adicional para detectar full/empty--
reg [2:0] w_ptr, r_ptr;
reg [7:0] fifo[4];
wire wrap_around;

// Valores por defecto
initial
begin
    w_ptr <= 0; r_ptr <= 0;
    r_data <= 0;
end

// Escritura
always@(posedge wr)
begin
    if(wr & !full)begin
        fifo[w_ptr[1:0]] <= w_data;
        w_ptr <= w_ptr + 1;
    end
end

// Lectura
always@(posedge rd)
begin
    if(rd & !empty) begin
        r_ptr <= r_ptr + 1;
    end
end

always@(*)
begin
    r_data <= fifo[r_ptr[1:0]];
end

//Chequeo para full y empty
assign wrap_around = w_ptr[2] ^ r_ptr[2];
assign full = wrap_around & (w_ptr[1:0] == r_ptr[1:0]);
assign empty = (w_ptr == r_ptr);
endmodule

TPI/TPI-Codigo/UARTComp/Transmitter.v
module Transmitter
(
    input       clk,            //i_Clock
    input       tx_start,       //i_Tx_DV
    input [7:0] din,            //i_Tx_Byte
    output      o_Tx_Active,    //bandera de transmitiendo
    output reg  Tx,             //Salida de dato en serie
    output      tx_done_tick      //
);

parameter CLKS_PER_BIT = 40;

//ESTADOS
parameter s_IDLE         = 3'b000;
parameter s_TX_START_BIT = 3'b001;
parameter s_TX_DATA_BITS = 3'b010;
parameter s_TX_STOP_BIT  = 3'b011;

reg [2:0]    r_SM_Main     = 0; //estado actual
reg [7:0]    r_Clock_Count = 0; //contador de ticks
reg [2:0]    r_Bit_Index   = 0; //puntero a bit del dato
reg [7:0]    r_Tx_Data     = 0; 
reg          r_Tx_Done     = 0;
reg          r_Tx_Active   = 0;
    
always @(posedge clk)
begin
    case (r_SM_Main)
    //ESTADO IDLE
    s_IDLE:
    begin
        Tx   <= 1'b1;  //Transmitir alto en IDLE
        r_Tx_Done     <= 1'b0;  //No transmitio nada
        r_Clock_Count <= 0;     //No cuenta ticks
        r_Bit_Index   <= 0;     //No avanza el bit de data
            
        if (tx_start == 1'b1)    //Si tx_start esta en alto
            begin
                r_Tx_Active <= 1'b1;            //Bandera de transmitiendo
                r_Tx_Data   <= din;             //Lee el dato de la FIFO
                r_SM_Main   <= s_TX_START_BIT;  //Pasa al estado START
            end
        else
            r_SM_Main <= s_IDLE;    //Bucle de estado
    end
        
    s_TX_START_BIT :
    begin
        Tx <= 1'b0;    //Envia el Start-bit
            
        // Espera CLKS_PER_BIT ticks para terminar el Start-bit
        if (r_Clock_Count < CLKS_PER_BIT-1)
            begin
                r_Clock_Count <= r_Clock_Count + 1;
                r_SM_Main     <= s_TX_START_BIT;
            end
        else    //Cuando termina el start bit
            begin
                r_Clock_Count <= 0;             //Reinicia el contador
                r_SM_Main     <= s_TX_DATA_BITS;//Pasa a estado DATA
            end
    end

    s_TX_DATA_BITS :
    begin
        // Envia a Tx el bit r_bit_index de Data
        Tx <= r_Tx_Data[r_Bit_Index];
        
        //Espera CLKS_PER_BIT ticks por cada bit de Data
        if (r_Clock_Count < CLKS_PER_BIT-1)
            begin
                r_Clock_Count <= r_Clock_Count + 1;
                r_SM_Main     <= s_TX_DATA_BITS;
            end
        else    //Cuando termina de enviar el bit
            begin
            r_Clock_Count <= 0; //Reinicia el contador de ticks

            if (r_Bit_Index < 7)    //Si quedan bits por mandar
                begin
                    r_Bit_Index <= r_Bit_Index + 1; //avanza el bit index
                    r_SM_Main   <= s_TX_DATA_BITS;  //bucle de estado
                end
            else    //Si ya envio todos los bits
                begin
                    r_Bit_Index <= 0;   //Reinicia el bit index
                    r_SM_Main   <= s_TX_STOP_BIT;   //Pasa al estado STOP
                end
            end
    end

    s_TX_STOP_BIT :
    begin
        //Envia el bit de Stop
        Tx <= 1'b1;
            
        //Envia el Stop-bit CLKS_PER_BIT ticks
        if (r_Clock_Count < CLKS_PER_BIT-1)
            begin
                r_Clock_Count <= r_Clock_Count + 1;
                r_SM_Main     <= s_TX_STOP_BIT;
            end
        else    //Cuando termina de enviar el Stop-bit
            begin
            r_Tx_Done     <= 1'b1;  //bandera de terminado
            r_Clock_Count <= 0;     //reinicia contador de ticks
            r_Tx_Active   <= 1'b0;  //bandera de no-transmitiendo
            r_SM_Main     <= s_IDLE;//Pasa a estado IDLE
            end
    end       

    default :
        r_SM_Main <= s_IDLE;
        
    endcase
end

assign o_Tx_Active = r_Tx_Active;
assign tx_done_tick   = r_Tx_Done;
   
endmodule

TPI/TPI-Codigo/UARTComp/Receiver.v
module Receiver
(
    input wire clk,             //i_clock
    input wire Rx,              //i_Rx_serial
    output wire Rx_done_tick,   //o_Rx_DV
    output [7:0] dout           //o_Rx_Byte
);

parameter CLKS_PER_BIT = 40;

//estados
parameter s_IDLE         = 3'b000;
parameter s_Rx_START_BIT = 3'b001;
parameter s_Rx_DATA_BITS = 3'b010;
parameter s_Rx_STOP_BIT  = 3'b011;

reg           r_Rx_Data_R = 1'b1;   //doble buffer
reg           r_Rx_Data   = 1'b1;

reg [7:0]     r_Clock_Count = 0;    //contador de ticks
reg [2:0]     r_Bit_Index   = 0;    //8 bits total
reg [7:0]     r_data_out    = 0;    //Data leida
reg           r_Rx_done_tick= 0;    //bandera de "termine de leer"
reg [2:0]     r_SM_Main     = 0;    //Estado actual

// Purpose: Double-register the incoming data.
// This allows it to be used in the UART Rx Clock Domain.
// (It removes problems caused by metastability)
// DE UNA
always @(posedge clk)
begin
    r_Rx_Data_R <= Rx;
    r_Rx_Data   <= r_Rx_Data_R;
end

// MAQUINA DE ESTADOS
always @(posedge clk)
begin
    case (r_SM_Main)
        s_IDLE:        // ESTADO IDLE
        begin
            r_Rx_done_tick       <= 1'b0;          //done = 0
            r_Clock_Count <= 0;
            r_Bit_Index   <= 0;
                
            if (r_Rx_Data == 1'b0)          // bit de inicio detectado
                r_SM_Main <= s_Rx_START_BIT;// Pasa al estado START
            else
                r_SM_Main <= s_IDLE;        // SI no sigue en IDLE
        end
    
        // ESTADO START
        // Check middle of start bit to make sure it's still low
        s_Rx_START_BIT :
        begin
            if (r_Clock_Count == (CLKS_PER_BIT-1)/2)    //si esta a la mitad del clk
                begin
                if (r_Rx_Data == 1'b0)  // si Rx esta en bajo
                    begin   // empieza el muestreo y pasa al leer DATA
                        //ACA ESTARIAMOS PARADOS A LA MITAD DEL BIT DE INICIO
                        r_Clock_Count <= 0;  // reset counter, found the middle
                        r_SM_Main     <= s_Rx_DATA_BITS;
                    end
                else
                    //ACA LEYO CUALQUIER COSA, VUELVE A IDLE
                    r_SM_Main <= s_IDLE;
                end
            else
                begin
                    r_Clock_Count <= r_Clock_Count + 1;
                    r_SM_Main     <= s_Rx_START_BIT;    // bucle de estado
                end
        end
        
        //ESTADO DATA
        // Wait CLKS_PER_BIT-1 clock cycles to sample serial data
        s_Rx_DATA_BITS :
        begin
            if (r_Clock_Count < CLKS_PER_BIT-1) //todavia no se fija el valor de Rx
                begin
                    r_Clock_Count <= r_Clock_Count + 1;
                    r_SM_Main     <= s_Rx_DATA_BITS;
                end
            else    //Llego a la mitad del siguiente clk
                begin
                    r_Clock_Count          <= 0;            //reinicia la cuenta del muestre
                    r_data_out[r_Bit_Index] <= r_Rx_Data;    //guardo el bit en el lugar al que apunta el bit index
                        
                    if (r_Bit_Index < 7)        //Si todavia no recibio toda la palabra
                        begin
                            r_Bit_Index <= r_Bit_Index + 1; //avanza el bit index
                            r_SM_Main   <= s_Rx_DATA_BITS;  //bucle de estado
                        end
                    else                        //Si recibio toda la palabra
                        begin
                            r_Bit_Index <= 0;   //reinicia el bit index
                            r_SM_Main   <= s_Rx_STOP_BIT;   //Pasa al estado de STOP
                        end
                end
        end
    
        //ESTADO STOP
        // Receive Stop bit.  Stop bit = 1
        s_Rx_STOP_BIT :
        begin
            // Wait CLKS_PER_BIT-1 clock cycles for Stop bit to finish
            if (r_Clock_Count < CLKS_PER_BIT-1) //si no llego a la mitad del bit de stop
                begin
                    r_Clock_Count <= r_Clock_Count + 1;
                    r_SM_Main     <= s_Rx_STOP_BIT;
                end
            else    //cuando llega a la mitad del bit de stop
                begin
                    r_Rx_done_tick       <= 1'b1;      //bandera de que termino de leer
                    r_Clock_Count <= 0;         //reinicia el contador
                    r_SM_Main     <= s_IDLE; //Pasa a CLEANUP
                end
        end
        
        default :
            r_SM_Main <= s_IDLE;
    endcase
end   

assign Rx_done_tick   = r_Rx_done_tick;
assign dout = r_data_out;

endmodule

TPI/TPI-Codigo/UART.v
`include "UARTComp/FIFO.v"
`include "UARTComp/Receiver.v"
`include "UARTComp/Transmitter.v"

module UART(
    input wire clk,
    input wire Rx,
    input wire rd,
    input [7:0] w_data,
    input wire wr,
    output [7:0] r_data,
    output wire rx_empty,
    output wire Tx
);

//----------cableciños----------
wire[7:0] s_dout;
wire s_rx_done_tick;
wire[7:0] s_din;
wire s_tx_done_tick;
wire s_tx_empty;
wire s_tx_start;
//------------------------------

reg r_tx_start;

Receiver receiver(
    .clk(clk),
    .Rx(Rx),
    .Rx_done_tick(s_rx_done_tick),
    .dout(s_dout)
);

Transmitter transmitter(
    .clk(clk),
    .Tx(Tx),
    .din(s_din),
    .tx_done_tick(s_tx_done_tick),
    .tx_start(s_tx_start)
);

FIFO fifoR(
    .wr(s_rx_done_tick),
    .rd(rd),
    .w_data(s_dout),
    .r_data(r_data),
    .full(full),
    .empty(empty)
);

FIFO fifoT(
    .wr(wr),
    .rd(s_tx_done_tick),
    .w_data(w_data),
    .r_data(s_din),
    .empty(s_tx_empty)
);

always @(*)
    r_tx_start <= ~s_tx_empty;

assign s_tx_start = r_tx_start;

endmodule

TPI/TPI-Codigo/UART_tb.v
`default_nettype none
`define DUMPSTR(x) `"x.vcd`"
`timescale 10 ns / 1 ns
// timescale <time_unit> / <time_precision>

module UART_tb();

//-- Simulation time: 1us (10 * 100ns)
parameter DURATION = 10000;

//-- Clock signal. It is not used in this simulation
reg clk = 0;
always #0.1 clk = ~clk;

// Top ports
reg Rx=1;
reg rd;
reg[7:0] w_data;
reg wr;
wire[7:0] r_data;
wire rx_empty;
wire Tx;

//-- Instantiate the unit to test
UART UUT (
    .clk(clk),
    .Rx(Rx),
    .rd(rd),
    .w_data(w_data),
    .wr(wr),
    .r_data(r_data),
    .rx_empty(rx_empty),
    .Tx(Tx)
);

initial begin
    //-- File were to store the simulation results
    $dumpfile(`DUMPSTR(`VCD_OUTPUT));
    $dumpvars(0, UART_tb);

    //Enviaremos 8'b10011010
    #2
    //start-bit
    Rx = 0;
    //Data
    #8
    Rx = 1;
    #8
    Rx = 0;
    #8
    Rx = 0;
    #8
    Rx = 1;
    #8
    Rx = 1;
    #8
    Rx = 0;
    #8
    Rx = 1;
    #8
    Rx = 0;
    //Stop-bit
    #8
    Rx = 1;

    //Transmitiremos 11010010
    #10
    w_data = 8'b11010010;
    #8
    wr = 1'b1;
    #1
    wr = 1'b0;

    #(DURATION) $display("End of simulation");
    $finish;
end

endmodule

TPI/TPI-Codigo/UART_tb.vcd
$date
	Tue Nov 07 23:49:57 2023
$end
$version
	Icarus Verilog
$end
$timescale
	1ps
$end
$scope module UART_tb $end
$var wire 1 ! rx_empty $end
$var wire 8 " r_data [7:0] $end
$var wire 1 # Tx $end
$var reg 1 $ Rx $end
$var reg 1 % clk $end
$var reg 1 & rd $end
$var reg 8 ' w_data [7:0] $end
$var reg 1 ( wr $end
$scope module UUT $end
$var wire 1 $ Rx $end
$var wire 1 % clk $end
$var wire 1 & rd $end
$var wire 1 ! rx_empty $end
$var wire 1 ) s_tx_start $end
$var wire 8 * w_data [7:0] $end
$var wire 1 ( wr $end
$var wire 1 + s_tx_empty $end
$var wire 1 , s_tx_done_tick $end
$var wire 1 - s_rx_done_tick $end
$var wire 8 . s_dout [7:0] $end
$var wire 8 / s_din [7:0] $end
$var wire 8 0 r_data [7:0] $end
$var wire 1 1 full $end
$var wire 1 2 empty $end
$var wire 1 # Tx $end
$var reg 1 3 r_tx_start $end
$scope module fifoR $end
$var wire 1 1 full $end
$var wire 1 & rd $end
$var wire 1 4 wrap_around $end
$var wire 1 - wr $end
$var wire 8 5 w_data [7:0] $end
$var wire 1 2 empty $end
$var reg 8 6 r_data [7:0] $end
$var reg 3 7 r_ptr [2:0] $end
$var reg 3 8 w_ptr [2:0] $end
$upscope $end
$scope module fifoT $end
$var wire 1 9 full $end
$var wire 8 : w_data [7:0] $end
$var wire 1 ( wr $end
$var wire 1 ; wrap_around $end
$var wire 1 , rd $end
$var wire 1 + empty $end
$var reg 8 < r_data [7:0] $end
$var reg 3 = r_ptr [2:0] $end
$var reg 3 > w_ptr [2:0] $end
$upscope $end
$scope module receiver $end
$var wire 1 $ Rx $end
$var wire 1 - Rx_done_tick $end
$var wire 1 % clk $end
$var wire 8 ? dout [7:0] $end
$var reg 3 @ r_Bit_Index [2:0] $end
$var reg 8 A r_Clock_Count [7:0] $end
$var reg 1 B r_Rx_Data $end
$var reg 1 C r_Rx_Data_R $end
$var reg 1 D r_Rx_done_tick $end
$var reg 3 E r_SM_Main [2:0] $end
$var reg 8 F r_data_out [7:0] $end
$upscope $end
$scope module transmitter $end
$var wire 1 % clk $end
$var wire 8 G din [7:0] $end
$var wire 1 H o_Tx_Active $end
$var wire 1 , tx_done_tick $end
$var wire 1 ) tx_start $end
$var reg 1 # Tx $end
$var reg 3 I r_Bit_Index [2:0] $end
$var reg 8 J r_Clock_Count [7:0] $end
$var reg 3 K r_SM_Main [2:0] $end
$var reg 1 L r_Tx_Active $end
$var reg 8 M r_Tx_Data [7:0] $end
$var reg 1 N r_Tx_Done $end
$upscope $end
$upscope $end
$upscope $end
$enddefinitions $end
#0
$dumpvars
0N
b0 M
0L
b0 K
b0 J
b0 I
0H
bx G
b0 F
b0 E
0D
1C
1B
b0 A
b0 @
b0 ?
b0 >
b0 =
bx <
0;
bx :
09
b0 8
b0 7
bx 6
b0 5
04
03
12
01
bx 0
bx /
b0 .
0-
0,
1+
bx *
0)
x(
bx '
x&
0%
1$
x#
bx "
z!
$end
#1000
1#
1%
#2000
0%
#3000
1%
#4000
0%
#5000
1%
#6000
0%
#7000
1%
#8000
0%
#9000
1%
#10000
0%
#11000
1%
#12000
0%
#13000
1%
#14000
0%
#15000
1%
#16000
0%
#17000
1%
#18000
0%
#19000
1%
#20000
0%
0$
#21000
0C
1%
#22000
0%
#23000
0B
1%
#24000
0%
#25000
b1 E
1%
#26000
0%
#27000
b1 A
1%
#28000
0%
#29000
b10 A
1%
#30000
0%
#31000
b11 A
1%
#32000
0%
#33000
b100 A
1%
#34000
0%
#35000
b101 A
1%
#36000
0%
#37000
b110 A
1%
#38000
0%
#39000
b111 A
1%
#40000
0%
#41000
b1000 A
1%
#42000
0%
#43000
b1001 A
1%
#44000
0%
#45000
b1010 A
1%
#46000
0%
#47000
b1011 A
1%
#48000
0%
#49000
b1100 A
1%
#50000
0%
#51000
b1101 A
1%
#52000
0%
#53000
b1110 A
1%
#54000
0%
#55000
b1111 A
1%
#56000
0%
#57000
b10000 A
1%
#58000
0%
#59000
b10001 A
1%
#60000
0%
#61000
b10010 A
1%
#62000
0%
#63000
b10011 A
1%
#64000
0%
#65000
b10 E
b0 A
1%
#66000
0%
#67000
b1 A
1%
#68000
0%
#69000
b10 A
1%
#70000
0%
#71000
b11 A
1%
#72000
0%
#73000
b100 A
1%
#74000
0%
#75000
b101 A
1%
#76000
0%
#77000
b110 A
1%
#78000
0%
#79000
b111 A
1%
#80000
0%
#81000
b1000 A
1%
#82000
0%
#83000
b1001 A
1%
#84000
0%
#85000
b1010 A
1%
#86000
0%
#87000
b1011 A
1%
#88000
0%
#89000
b1100 A
1%
#90000
0%
#91000
b1101 A
1%
#92000
0%
#93000
b1110 A
1%
#94000
0%
#95000
b1111 A
1%
#96000
0%
#97000
b10000 A
1%
#98000
0%
#99000
b10001 A
1%
#100000
0%
1$
#101000
1C
b10010 A
1%
#102000
0%
#103000
b10011 A
1B
1%
#104000
0%
#105000
b10100 A
1%
#106000
0%
#107000
b10101 A
1%
#108000
0%
#109000
b10110 A
1%
#110000
0%
#111000
b10111 A
1%
#112000
0%
#113000
b11000 A
1%
#114000
0%
#115000
b11001 A
1%
#116000
0%
#117000
b11010 A
1%
#118000
0%
#119000
b11011 A
1%
#120000
0%
#121000
b11100 A
1%
#122000
0%
#123000
b11101 A
1%
#124000
0%
#125000
b11110 A
1%
#126000
0%
#127000
b11111 A
1%
#128000
0%
#129000
b100000 A
1%
#130000
0%
#131000
b100001 A
1%
#132000
0%
#133000
b100010 A
1%
#134000
0%
#135000
b100011 A
1%
#136000
0%
#137000
b100100 A
1%
#138000
0%
#139000
b100101 A
1%
#140000
0%
#141000
b100110 A
1%
#142000
0%
#143000
b100111 A
1%
#144000
0%
#145000
b1 @
b1 .
b1 5
b1 ?
b1 F
b0 A
1%
#146000
0%
#147000
b1 A
1%
#148000
0%
#149000
b10 A
1%
#150000
0%
#151000
b11 A
1%
#152000
0%
#153000
b100 A
1%
#154000
0%
#155000
b101 A
1%
#156000
0%
#157000
b110 A
1%
#158000
0%
#159000
b111 A
1%
#160000
0%
#161000
b1000 A
1%
#162000
0%
#163000
b1001 A
1%
#164000
0%
#165000
b1010 A
1%
#166000
0%
#167000
b1011 A
1%
#168000
0%
#169000
b1100 A
1%
#170000
0%
#171000
b1101 A
1%
#172000
0%
#173000
b1110 A
1%
#174000
0%
#175000
b1111 A
1%
#176000
0%
#177000
b10000 A
1%
#178000
0%
#179000
b10001 A
1%
#180000
0%
0$
#181000
0C
b10010 A
1%
#182000
0%
#183000
b10011 A
0B
1%
#184000
0%
#185000
b10100 A
1%
#186000
0%
#187000
b10101 A
1%
#188000
0%
#189000
b10110 A
1%
#190000
0%
#191000
b10111 A
1%
#192000
0%
#193000
b11000 A
1%
#194000
0%
#195000
b11001 A
1%
#196000
0%
#197000
b11010 A
1%
#198000
0%
#199000
b11011 A
1%
#200000
0%
#201000
b11100 A
1%
#202000
0%
#203000
b11101 A
1%
#204000
0%
#205000
b11110 A
1%
#206000
0%
#207000
b11111 A
1%
#208000
0%
#209000
b100000 A
1%
#210000
0%
#211000
b100001 A
1%
#212000
0%
#213000
b100010 A
1%
#214000
0%
#215000
b100011 A
1%
#216000
0%
#217000
b100100 A
1%
#218000
0%
#219000
b100101 A
1%
#220000
0%
#221000
b100110 A
1%
#222000
0%
#223000
b100111 A
1%
#224000
0%
#225000
b10 @
b0 A
1%
#226000
0%
#227000
b1 A
1%
#228000
0%
#229000
b10 A
1%
#230000
0%
#231000
b11 A
1%
#232000
0%
#233000
b100 A
1%
#234000
0%
#235000
b101 A
1%
#236000
0%
#237000
b110 A
1%
#238000
0%
#239000
b111 A
1%
#240000
0%
#241000
b1000 A
1%
#242000
0%
#243000
b1001 A
1%
#244000
0%
#245000
b1010 A
1%
#246000
0%
#247000
b1011 A
1%
#248000
0%
#249000
b1100 A
1%
#250000
0%
#251000
b1101 A
1%
#252000
0%
#253000
b1110 A
1%
#254000
0%
#255000
b1111 A
1%
#256000
0%
#257000
b10000 A
1%
#258000
0%
#259000
b10001 A
1%
#260000
0%
#261000
b10010 A
1%
#262000
0%
#263000
b10011 A
1%
#264000
0%
#265000
b10100 A
1%
#266000
0%
#267000
b10101 A
1%
#268000
0%
#269000
b10110 A
1%
#270000
0%
#271000
b10111 A
1%
#272000
0%
#273000
b11000 A
1%
#274000
0%
#275000
b11001 A
1%
#276000
0%
#277000
b11010 A
1%
#278000
0%
#279000
b11011 A
1%
#280000
0%
#281000
b11100 A
1%
#282000
0%
#283000
b11101 A
1%
#284000
0%
#285000
b11110 A
1%
#286000
0%
#287000
b11111 A
1%
#288000
0%
#289000
b100000 A
1%
#290000
0%
#291000
b100001 A
1%
#292000
0%
#293000
b100010 A
1%
#294000
0%
#295000
b100011 A
1%
#296000
0%
#297000
b100100 A
1%
#298000
0%
#299000
b100101 A
1%
#300000
0%
#301000
b100110 A
1%
#302000
0%
#303000
b100111 A
1%
#304000
0%
#305000
b11 @
b0 A
1%
#306000
0%
#307000
b1 A
1%
#308000
0%
#309000
b10 A
1%
#310000
0%
#311000
b11 A
1%
#312000
0%
#313000
b100 A
1%
#314000
0%
#315000
b101 A
1%
#316000
0%
#317000
b110 A
1%
#318000
0%
#319000
b111 A
1%
#320000
0%
#321000
b1000 A
1%
#322000
0%
#323000
b1001 A
1%
#324000
0%
#325000
b1010 A
1%
#326000
0%
#327000
b1011 A
1%
#328000
0%
#329000
b1100 A
1%
#330000
0%
#331000
b1101 A
1%
#332000
0%
#333000
b1110 A
1%
#334000
0%
#335000
b1111 A
1%
#336000
0%
#337000
b10000 A
1%
#338000
0%
#339000
b10001 A
1%
#340000
0%
1$
#341000
1C
b10010 A
1%
#342000
0%
#343000
b10011 A
1B
1%
#344000
0%
#345000
b10100 A
1%
#346000
0%
#347000
b10101 A
1%
#348000
0%
#349000
b10110 A
1%
#350000
0%
#351000
b10111 A
1%
#352000
0%
#353000
b11000 A
1%
#354000
0%
#355000
b11001 A
1%
#356000
0%
#357000
b11010 A
1%
#358000
0%
#359000
b11011 A
1%
#360000
0%
#361000
b11100 A
1%
#362000
0%
#363000
b11101 A
1%
#364000
0%
#365000
b11110 A
1%
#366000
0%
#367000
b11111 A
1%
#368000
0%
#369000
b100000 A
1%
#370000
0%
#371000
b100001 A
1%
#372000
0%
#373000
b100010 A
1%
#374000
0%
#375000
b100011 A
1%
#376000
0%
#377000
b100100 A
1%
#378000
0%
#379000
b100101 A
1%
#380000
0%
#381000
b100110 A
1%
#382000
0%
#383000
b100111 A
1%
#384000
0%
#385000
b100 @
b1001 .
b1001 5
b1001 ?
b1001 F
b0 A
1%
#386000
0%
#387000
b1 A
1%
#388000
0%
#389000
b10 A
1%
#390000
0%
#391000
b11 A
1%
#392000
0%
#393000
b100 A
1%
#394000
0%
#395000
b101 A
1%
#396000
0%
#397000
b110 A
1%
#398000
0%
#399000
b111 A
1%
#400000
0%
#401000
b1000 A
1%
#402000
0%
#403000
b1001 A
1%
#404000
0%
#405000
b1010 A
1%
#406000
0%
#407000
b1011 A
1%
#408000
0%
#409000
b1100 A
1%
#410000
0%
#411000
b1101 A
1%
#412000
0%
#413000
b1110 A
1%
#414000
0%
#415000
b1111 A
1%
#416000
0%
#417000
b10000 A
1%
#418000
0%
#419000
b10001 A
1%
#420000
0%
#421000
b10010 A
1%
#422000
0%
#423000
b10011 A
1%
#424000
0%
#425000
b10100 A
1%
#426000
0%
#427000
b10101 A
1%
#428000
0%
#429000
b10110 A
1%
#430000
0%
#431000
b10111 A
1%
#432000
0%
#433000
b11000 A
1%
#434000
0%
#435000
b11001 A
1%
#436000
0%
#437000
b11010 A
1%
#438000
0%
#439000
b11011 A
1%
#440000
0%
#441000
b11100 A
1%
#442000
0%
#443000
b11101 A
1%
#444000
0%
#445000
b11110 A
1%
#446000
0%
#447000
b11111 A
1%
#448000
0%
#449000
b100000 A
1%
#450000
0%
#451000
b100001 A
1%
#452000
0%
#453000
b100010 A
1%
#454000
0%
#455000
b100011 A
1%
#456000
0%
#457000
b100100 A
1%
#458000
0%
#459000
b100101 A
1%
#460000
0%
#461000
b100110 A
1%
#462000
0%
#463000
b100111 A
1%
#464000
0%
#465000
b101 @
b11001 .
b11001 5
b11001 ?
b11001 F
b0 A
1%
#466000
0%
#467000
b1 A
1%
#468000
0%
#469000
b10 A
1%
#470000
0%
#471000
b11 A
1%
#472000
0%
#473000
b100 A
1%
#474000
0%
#475000
b101 A
1%
#476000
0%
#477000
b110 A
1%
#478000
0%
#479000
b111 A
1%
#480000
0%
#481000
b1000 A
1%
#482000
0%
#483000
b1001 A
1%
#484000
0%
#485000
b1010 A
1%
#486000
0%
#487000
b1011 A
1%
#488000
0%
#489000
b1100 A
1%
#490000
0%
#491000
b1101 A
1%
#492000
0%
#493000
b1110 A
1%
#494000
0%
#495000
b1111 A
1%
#496000
0%
#497000
b10000 A
1%
#498000
0%
#499000
b10001 A
1%
#500000
0%
0$
#501000
0C
b10010 A
1%
#502000
0%
#503000
b10011 A
0B
1%
#504000
0%
#505000
b10100 A
1%
#506000
0%
#507000
b10101 A
1%
#508000
0%
#509000
b10110 A
1%
#510000
0%
#511000
b10111 A
1%
#512000
0%
#513000
b11000 A
1%
#514000
0%
#515000
b11001 A
1%
#516000
0%
#517000
b11010 A
1%
#518000
0%
#519000
b11011 A
1%
#520000
0%
#521000
b11100 A
1%
#522000
0%
#523000
b11101 A
1%
#524000
0%
#525000
b11110 A
1%
#526000
0%
#527000
b11111 A
1%
#528000
0%
#529000
b100000 A
1%
#530000
0%
#531000
b100001 A
1%
#532000
0%
#533000
b100010 A
1%
#534000
0%
#535000
b100011 A
1%
#536000
0%
#537000
b100100 A
1%
#538000
0%
#539000
b100101 A
1%
#540000
0%
#541000
b100110 A
1%
#542000
0%
#543000
b100111 A
1%
#544000
0%
#545000
b110 @
b0 A
1%
#546000
0%
#547000
b1 A
1%
#548000
0%
#549000
b10 A
1%
#550000
0%
#551000
b11 A
1%
#552000
0%
#553000
b100 A
1%
#554000
0%
#555000
b101 A
1%
#556000
0%
#557000
b110 A
1%
#558000
0%
#559000
b111 A
1%
#560000
0%
#561000
b1000 A
1%
#562000
0%
#563000
b1001 A
1%
#564000
0%
#565000
b1010 A
1%
#566000
0%
#567000
b1011 A
1%
#568000
0%
#569000
b1100 A
1%
#570000
0%
#571000
b1101 A
1%
#572000
0%
#573000
b1110 A
1%
#574000
0%
#575000
b1111 A
1%
#576000
0%
#577000
b10000 A
1%
#578000
0%
#579000
b10001 A
1%
#580000
0%
1$
#581000
1C
b10010 A
1%
#582000
0%
#583000
b10011 A
1B
1%
#584000
0%
#585000
b10100 A
1%
#586000
0%
#587000
b10101 A
1%
#588000
0%
#589000
b10110 A
1%
#590000
0%
#591000
b10111 A
1%
#592000
0%
#593000
b11000 A
1%
#594000
0%
#595000
b11001 A
1%
#596000
0%
#597000
b11010 A
1%
#598000
0%
#599000
b11011 A
1%
#600000
0%
#601000
b11100 A
1%
#602000
0%
#603000
b11101 A
1%
#604000
0%
#605000
b11110 A
1%
#606000
0%
#607000
b11111 A
1%
#608000
0%
#609000
b100000 A
1%
#610000
0%
#611000
b100001 A
1%
#612000
0%
#613000
b100010 A
1%
#614000
0%
#615000
b100011 A
1%
#616000
0%
#617000
b100100 A
1%
#618000
0%
#619000
b100101 A
1%
#620000
0%
#621000
b100110 A
1%
#622000
0%
#623000
b100111 A
1%
#624000
0%
#625000
b111 @
b1011001 .
b1011001 5
b1011001 ?
b1011001 F
b0 A
1%
#626000
0%
#627000
b1 A
1%
#628000
0%
#629000
b10 A
1%
#630000
0%
#631000
b11 A
1%
#632000
0%
#633000
b100 A
1%
#634000
0%
#635000
b101 A
1%
#636000
0%
#637000
b110 A
1%
#638000
0%
#639000
b111 A
1%
#640000
0%
#641000
b1000 A
1%
#642000
0%
#643000
b1001 A
1%
#644000
0%
#645000
b1010 A
1%
#646000
0%
#647000
b1011 A
1%
#648000
0%
#649000
b1100 A
1%
#650000
0%
#651000
b1101 A
1%
#652000
0%
#653000
b1110 A
1%
#654000
0%
#655000
b1111 A
1%
#656000
0%
#657000
b10000 A
1%
#658000
0%
#659000
b10001 A
1%
#660000
0%
0$
#661000
0C
b10010 A
1%
#662000
0%
#663000
b10011 A
0B
1%
#664000
0%
#665000
b10100 A
1%
#666000
0%
#667000
b10101 A
1%
#668000
0%
#669000
b10110 A
1%
#670000
0%
#671000
b10111 A
1%
#672000
0%
#673000
b11000 A
1%
#674000
0%
#675000
b11001 A
1%
#676000
0%
#677000
b11010 A
1%
#678000
0%
#679000
b11011 A
1%
#680000
0%
#681000
b11100 A
1%
#682000
0%
#683000
b11101 A
1%
#684000
0%
#685000
b11110 A
1%
#686000
0%
#687000
b11111 A
1%
#688000
0%
#689000
b100000 A
1%
#690000
0%
#691000
b100001 A
1%
#692000
0%
#693000
b100010 A
1%
#694000
0%
#695000
b100011 A
1%
#696000
0%
#697000
b100100 A
1%
#698000
0%
#699000
b100101 A
1%
#700000
0%
#701000
b100110 A
1%
#702000
0%
#703000
b100111 A
1%
#704000
0%
#705000
b11 E
b0 @
b0 A
1%
#706000
0%
#707000
b1 A
1%
#708000
0%
#709000
b10 A
1%
#710000
0%
#711000
b11 A
1%
#712000
0%
#713000
b100 A
1%
#714000
0%
#715000
b101 A
1%
#716000
0%
#717000
b110 A
1%
#718000
0%
#719000
b111 A
1%
#720000
0%
#721000
b1000 A
1%
#722000
0%
#723000
b1001 A
1%
#724000
0%
#725000
b1010 A
1%
#726000
0%
#727000
b1011 A
1%
#728000
0%
#729000
b1100 A
1%
#730000
0%
#731000
b1101 A
1%
#732000
0%
#733000
b1110 A
1%
#734000
0%
#735000
b1111 A
1%
#736000
0%
#737000
b10000 A
1%
#738000
0%
#739000
b10001 A
1%
#740000
0%
1$
#741000
1C
b10010 A
1%
#742000
0%
#743000
b10011 A
1B
1%
#744000
0%
#745000
b10100 A
1%
#746000
0%
#747000
b10101 A
1%
#748000
0%
#749000
b10110 A
1%
#750000
0%
#751000
b10111 A
1%
#752000
0%
#753000
b11000 A
1%
#754000
0%
#755000
b11001 A
1%
#756000
0%
#757000
b11010 A
1%
#758000
0%
#759000
b11011 A
1%
#760000
0%
#761000
b11100 A
1%
#762000
0%
#763000
b11101 A
1%
#764000
0%
#765000
b11110 A
1%
#766000
0%
#767000
b11111 A
1%
#768000
0%
#769000
b100000 A
1%
#770000
0%
#771000
b100001 A
1%
#772000
0%
#773000
b100010 A
1%
#774000
0%
#775000
b100011 A
1%
#776000
0%
#777000
b100100 A
1%
#778000
0%
#779000
b100101 A
1%
