guia7/Components/PC.v
/*module contador (
   input wire clk,
   input reg[15:0] pcNext,
   output reg[15:0] pc
);*/
module PC(
    input wire clk,
    input [15:0] pcNext,
    output [15:0] pc
);

reg[15:0] count_reg = 16'h0;

always @(posedge clk)
begin
    if(pcNext != 16'h0000)
    begin
        count_reg <= pcNext;
    end
    count_reg <= count_reg + 4;
end
assign pc = count_reg;

endmodule
//Banco de registros
//Con a1 defino el operando 1
//imm[11:0]|rs1|funct3|rd(registro destino)|opcode
//funct7|rs2|rs1|funct3|rd|opcode
//rs2 es a2, rs1 es a1, rd es a3
//A la alu le tengo que agregar una senial
//de control que me permita ver que operacion
//realiza. Entre estas tiene que estar set less than
//suma, resta por complemento a 2, and y or
////////
//Voy a construir un procesador monociclo, es 
//directamente un circuito combinacional
//en las diapositivas para hacer el datapath
//deja las memorias por un lado y la parte logica 
//por otro

guia7/Components/PC_tb.v
`default_nettype none
`define DUMPSTR(x) `"x.vcd`"
`timescale 100 ns / 10 ns
// timescale <time_unit> / <time_precision>

module PC_tb();

//-- Simulation time: 1us (10 * 100ns)
parameter DURATION = 10;

//-- Clock signal. It is not used in this simulation
reg clk = 0;
always #0.5 clk = ~clk;

// contador ports
reg[15:0] pcNext;
wire[15:0] pc;

//-- Instantiate the unit to test
PC UUT (
  .clk(clk),
  .pcNext(pcNext),
  .pc(pc)
);

integer i;

initial begin

  //-- File were to store the simulation results
  $dumpfile(`DUMPSTR(`VCD_OUTPUT));
  $dumpvars(0, PC_tb);

  for (i=0; i<100; i=i+1)
  begin
    $display ("Current loop # %0d", i);
    $display ("Current loop # %0b", i);
    
    #0
    pcNext = 4'b0000;

    #1
    pcNext = 4'b0100;

    #2
    pcNext = 4'b1000;
  end

   #(DURATION) $display("End of simulation");
  $finish;
end

endmodule

TPI (2023)/TPI-Codigo/Components/PC_tb.vcd
$date
	Tue Oct 17 10:18:09 2023
$end
$version
	Icarus Verilog
$end
$timescale
	1ps
$end
$scope module PC_tb $end
$var wire 16 ! pc [15:0] $end
$var reg 1 " clk $end
$var reg 16 # pcNext [15:0] $end
$var integer 32 $ i [31:0] $end
$scope module UUT $end
$var wire 1 " clk $end
$var wire 16 % pc [15:0] $end
$var wire 16 & pcNext [15:0] $end
$var reg 16 ' count_reg [15:0] $end
$upscope $end
$upscope $end
$enddefinitions $end
#0
$dumpvars
b0 '
b0 &
b0 %
b0 $
b0 #
0"
b0 !
$end
#50000
1"
#100000
0"
b100 #
b100 &
#150000
b100 !
b100 %
b100 '
1"
#200000
0"
#250000
1"
#300000
0"
b1 $
b0 #
b0 &
#350000
b0 !
b0 %
b0 '
1"
#400000
0"
b100 #
b100 &
#450000
b100 !
b100 %
b100 '
1"
#500000
0"
#550000
1"
#600000
0"
b10 $
b0 #
b0 &
#650000
b0 !
b0 %
b0 '
1"
#700000
0"
b100 #
b100 &
#750000
b100 !
b100 %
b100 '
1"
#800000
0"
#850000
1"
#900000
0"
b11 $
b0 #
b0 &
#950000
b0 !
b0 %
b0 '
1"
#1000000
0"
b100 #
b100 &
#1050000
b100 !
b100 %
b100 '
1"
#1100000
0"
#1150000
1"
#1200000
0"
b100 $
b0 #
b0 &
#1250000
b0 !
b0 %
b0 '
1"
#1300000
0"
b100 #
b100 &
#1350000
b100 !
b100 %
b100 '
1"
#1400000
0"
#1450000
1"
#1500000
0"
b101 $
b0 #
b0 &
#1550000
b0 !
b0 %
b0 '
1"
#1600000
0"
b100 #
b100 &
#1650000
b100 !
b100 %
b100 '
1"
#1700000
0"
#1750000
1"
#1800000
0"
b110 $
b0 #
b0 &
#1850000
b0 !
b0 %
b0 '
1"
#1900000
0"
b100 #
b100 &
#1950000
b100 !
b100 %
b100 '
1"
#2000000
0"
#2050000
1"
#2100000
0"
b111 $
b0 #
b0 &
#2150000
b0 !
b0 %
b0 '
1"
#2200000
0"
b100 #
b100 &
#2250000
b100 !
b100 %
b100 '
1"
#2300000
0"
#2350000
1"
#2400000
0"
b1000 $
b0 #
b0 &
#2450000
b0 !
b0 %
b0 '
1"
#2500000
0"
b100 #
b100 &
#2550000
b100 !
b100 %
b100 '
1"
#2600000
0"
#2650000
1"
#2700000
0"
b1001 $
b0 #
b0 &
#2750000
b0 !
b0 %
b0 '
1"
#2800000
0"
b100 #
b100 &
#2850000
b100 !
b100 %
b100 '
1"
#2900000
0"
#2950000
1"
#3000000
0"
b1010 $
b0 #
b0 &
#3050000
b0 !
b0 %
b0 '
1"
#3100000
0"
b100 #
b100 &
#3150000
b100 !
b100 %
b100 '
1"
#3200000
0"
#3250000
1"
#3300000
0"
b1011 $
b0 #
b0 &
#3350000
b0 !
b0 %
b0 '
1"
#3400000
0"
b100 #
b100 &
#3450000
b100 !
b100 %
b100 '
1"
#3500000
0"
#3550000
1"
#3600000
0"
b1100 $
b0 #
b0 &
#3650000
b0 !
b0 %
b0 '
1"
#3700000
0"
b100 #
b100 &
#3750000
b100 !
b100 %
b100 '
1"
#3800000
0"
#3850000
1"
#3900000
0"
b1101 $
b0 #
b0 &
#3950000
b0 !
b0 %
b0 '
1"
#4000000
0"
b100 #
b100 &
#4050000
b100 !
b100 %
b100 '
1"
#4100000
0"
#4150000
1"
#4200000
0"
b1110 $
b0 #
b0 &
#4250000
b0 !
b0 %
b0 '
1"
#4300000
0"
b100 #
b100 &
#4350000
b100 !
b100 %
b100 '
1"
#4400000
0"
#4450000
1"
#4500000
0"
b1111 $
b0 #
b0 &
#4550000
b0 !
b0 %
b0 '
1"
#4600000
0"
b100 #
b100 &
#4650000
b100 !
b100 %
b100 '
1"
#4700000
0"
#4750000
1"
#4800000
0"
b10000 $
b0 #
b0 &
#4850000
b0 !
b0 %
b0 '
1"
#4900000
0"
b100 #
b100 &
#4950000
b100 !
b100 %
b100 '
1"
#5000000
0"
#5050000
1"
#5100000
0"
b10001 $
b0 #
b0 &
#5150000
b0 !
b0 %
b0 '
1"
#5200000
0"
b100 #
b100 &
#5250000
b100 !
b100 %
b100 '
1"
#5300000
0"
#5350000
1"
#5400000
0"
b10010 $
b0 #
b0 &
#5450000
b0 !
b0 %
b0 '
1"
#5500000
0"
b100 #
b100 &
#5550000
b100 !
b100 %
b100 '
1"
#5600000
0"
#5650000
1"
#5700000
0"
b10011 $
b0 #
b0 &
#5750000
b0 !
b0 %
b0 '
1"
#5800000
0"
b100 #
b100 &
#5850000
b100 !
b100 %
b100 '
1"
#5900000
0"
#5950000
1"
#6000000
0"
b10100 $
b0 #
b0 &
#6050000
b0 !
b0 %
b0 '
1"
#6100000
0"
b100 #
b100 &
#6150000
b100 !
b100 %
b100 '
1"
#6200000
0"
#6250000
1"
#6300000
0"
b10101 $
b0 #
b0 &
#6350000
b0 !
b0 %
b0 '
1"
#6400000
0"
b100 #
b100 &
#6450000
b100 !
b100 %
b100 '
1"
#6500000
0"
#6550000
1"
#6600000
0"
b10110 $
b0 #
b0 &
#6650000
b0 !
b0 %
b0 '
1"
#6700000
0"
b100 #
b100 &
#6750000
b100 !
b100 %
b100 '
1"
#6800000
0"
#6850000
1"
#6900000
0"
b10111 $
b0 #
b0 &
#6950000
b0 !
b0 %
b0 '
1"
#7000000
0"
b100 #
b100 &
#7050000
b100 !
b100 %
b100 '
1"
#7100000
0"
#7150000
1"
#7200000
0"
b11000 $
b0 #
b0 &
#7250000
b0 !
b0 %
b0 '
1"
#7300000
0"
b100 #
b100 &
#7350000
b100 !
b100 %
b100 '
1"
#7400000
0"
#7450000
1"
#7500000
0"
b11001 $
b0 #
b0 &
#7550000
b0 !
b0 %
b0 '
1"
#7600000
0"
b100 #
b100 &
#7650000
b100 !
b100 %
b100 '
1"
#7700000
0"
#7750000
1"
#7800000
0"
b11010 $
b0 #
b0 &
#7850000
b0 !
b0 %
b0 '
1"
#7900000
0"
b100 #
b100 &
#7950000
b100 !
b100 %
b100 '
1"
#8000000
0"
#8050000
1"
#8100000
0"
b11011 $
b0 #
b0 &
#8150000
b0 !
b0 %
b0 '
1"
#8200000
0"
b100 #
b100 &
#8250000
b100 !
b100 %
b100 '
1"
#8300000
0"
#8350000
1"
#8400000
0"
b11100 $
b0 #
b0 &
#8450000
b0 !
b0 %
b0 '
1"
#8500000
0"
b100 #
b100 &
#8550000
b100 !
b100 %
b100 '
1"
#8600000
0"
#8650000
1"
#8700000
0"
b11101 $
b0 #
b0 &
#8750000
b0 !
b0 %
b0 '
1"
#8800000
0"
b100 #
b100 &
#8850000
b100 !
b100 %
b100 '
1"
#8900000
0"
#8950000
1"
#9000000
0"
b11110 $
b0 #
b0 &
#9050000
b0 !
b0 %
b0 '
1"
#9100000
0"
b100 #
b100 &
#9150000
b100 !
b100 %
b100 '
1"
#9200000
0"
#9250000
1"
#9300000
0"
b11111 $
b0 #
b0 &
#9350000
b0 !
b0 %
b0 '
1"
#9400000
0"
b100 #
b100 &
#9450000
b100 !
b100 %
b100 '
1"
#9500000
0"
#9550000
1"
#9600000
0"
b100000 $
b0 #
b0 &
#9650000
b0 !
b0 %
b0 '
1"
#9700000
0"
b100 #
b100 &
#9750000
b100 !
b100 %
b100 '
1"
#9800000
0"
#9850000
1"
#9900000
0"
b100001 $
b0 #
b0 &
#9950000
b0 !
b0 %
b0 '
1"
#10000000
0"
b100 #
b100 &
#10050000
b100 !
b100 %
b100 '
1"
#10100000
0"
#10150000
1"
#10200000
0"
b100010 $
b0 #
b0 &
#10250000
b0 !
b0 %
b0 '
1"
#10300000
0"
b100 #
b100 &
#10350000
b100 !
b100 %
b100 '
1"
#10400000
0"
#10450000
1"
#10500000
0"
b100011 $
b0 #
b0 &
#10550000
b0 !
b0 %
b0 '
1"
#10600000
0"
b100 #
b100 &
#10650000
b100 !
b100 %
b100 '
1"
#10700000
0"
#10750000
1"
#10800000
0"
b100100 $
b0 #
b0 &
#10850000
b0 !
b0 %
b0 '
1"
#10900000
0"
b100 #
b100 &
#10950000
b100 !
b100 %
b100 '
1"
#11000000
0"
#11050000
1"
#11100000
0"
b100101 $
b0 #
b0 &
#11150000
b0 !
b0 %
b0 '
1"
#11200000
0"
b100 #
b100 &
#11250000
b100 !
b100 %
b100 '
1"
#11300000
0"
#11350000
1"
#11400000
0"
b100110 $
b0 #
b0 &
#11450000
b0 !
b0 %
b0 '
1"
#11500000
0"
b100 #
b100 &
#11550000
b100 !
b100 %
b100 '
1"
#11600000
0"
#11650000
1"
#11700000
0"
b100111 $
b0 #
b0 &
#11750000
b0 !
b0 %
b0 '
1"
#11800000
0"
b100 #
b100 &
#11850000
b100 !
b100 %
b100 '
1"
#11900000
0"
#11950000
1"
#12000000
0"
b101000 $
b0 #
b0 &
#12050000
b0 !
b0 %
b0 '
1"
#12100000
0"
b100 #
b100 &
#12150000
b100 !
b100 %
b100 '
1"
#12200000
0"
#12250000
1"
#12300000
0"
b101001 $
b0 #
b0 &
#12350000
b0 !
b0 %
b0 '
1"
#12400000
0"
b100 #
b100 &
#12450000
b100 !
b100 %
b100 '
1"
#12500000
0"
#12550000
1"
#12600000
0"
b101010 $
b0 #
b0 &
#12650000
b0 !
b0 %
b0 '
1"
#12700000
0"
b100 #
b100 &
#12750000
b100 !
b100 %
b100 '
1"
#12800000
0"
#12850000
1"
#12900000
0"
b101011 $
b0 #
b0 &
#12950000
b0 !
b0 %
b0 '
1"
#13000000
0"
b100 #
b100 &
#13050000
b100 !
b100 %
b100 '
1"
#13100000
0"
#13150000
1"
#13200000
0"
b101100 $
b0 #
b0 &
#13250000
b0 !
b0 %
b0 '
1"
#13300000
0"
b100 #
b100 &
#13350000
b100 !
b100 %
b100 '
1"
#13400000
0"
#13450000
1"
#13500000
0"
b101101 $
b0 #
b0 &
#13550000
b0 !
b0 %
b0 '
1"
#13600000
0"
b100 #
b100 &
#13650000
b100 !
b100 %
b100 '
1"
#13700000
0"
#13750000
1"
#13800000
0"
b101110 $
b0 #
b0 &
#13850000
b0 !
b0 %
b0 '
1"
#13900000
0"
b100 #
b100 &
#13950000
b100 !
b100 %
b100 '
1"
#14000000
0"
#14050000
1"
#14100000
0"
b101111 $
b0 #
b0 &
#14150000
b0 !
b0 %
b0 '
1"
#14200000
0"
b100 #
b100 &
#14250000
b100 !
b100 %
b100 '
1"
#14300000
0"
#14350000
1"
#14400000
0"
b110000 $
b0 #
b0 &
#14450000
b0 !
b0 %
b0 '
1"
#14500000
0"
b100 #
b100 &
#14550000
b100 !
b100 %
b100 '
1"
#14600000
0"
#14650000
1"
#14700000
0"
b110001 $
b0 #
b0 &
#14750000
b0 !
b0 %
b0 '
1"
#14800000
0"
b100 #
b100 &
#14850000
b100 !
b100 %
b100 '
1"
#14900000
0"
#14950000
1"
#15000000
0"
b110010 $
b0 #
b0 &
#15050000
b0 !
b0 %
b0 '
1"
#15100000
0"
b100 #
b100 &
#15150000
b100 !
b100 %
b100 '
1"
#15200000
0"
#15250000
1"
#15300000
0"
b110011 $
b0 #
b0 &
#15350000
b0 !
b0 %
b0 '
1"
#15400000
0"
b100 #
b100 &
#15450000
b100 !
b100 %
b100 '
1"
#15500000
0"
#15550000
1"
#15600000
0"
b110100 $
b0 #
b0 &
#15650000
b0 !
b0 %
b0 '
1"
#15700000
0"
b100 #
b100 &
#15750000
b100 !
b100 %
b100 '
1"
#15800000
0"
#15850000
1"
#15900000
0"
b110101 $
b0 #
b0 &
#15950000
b0 !
b0 %
b0 '
1"
#16000000
0"
b100 #
b100 &
#16050000
b100 !
b100 %
b100 '
1"
#16100000
0"
#16150000
1"
#16200000
0"
b110110 $
b0 #
b0 &
#16250000
b0 !
b0 %
b0 '
1"
#16300000
0"
b100 #
b100 &
#16350000
b100 !
b100 %
b100 '
1"
#16400000
0"
#16450000
1"
#16500000
0"
b110111 $
b0 #
b0 &
#16550000
b0 !
b0 %
b0 '
1"
#16600000
0"
b100 #
b100 &
#16650000
b100 !
b100 %
b100 '
1"
#16700000
0"
#16750000
1"
#16800000
0"
b111000 $
b0 #
b0 &
#16850000
b0 !
b0 %
b0 '
1"
#16900000
0"
b100 #
b100 &
#16950000
b100 !
b100 %
b100 '
1"
#17000000
0"
#17050000
1"
#17100000
0"
b111001 $
b0 #
b0 &
#17150000
b0 !
b0 %
b0 '
1"
#17200000
0"
b100 #
b100 &
#17250000
b100 !
b100 %
b100 '
1"
#17300000
0"
#17350000
1"
#17400000
0"
b111010 $
b0 #
b0 &
#17450000
b0 !
b0 %
b0 '
1"
#17500000
0"
b100 #
b100 &
#17550000
b100 !
b100 %
b100 '
1"
#17600000
0"
#17650000
1"
#17700000
0"
b111011 $
b0 #
b0 &
#17750000
b0 !
b0 %
b0 '
1"
#17800000
0"
b100 #
b100 &
#17850000
b100 !
b100 %
b100 '
1"
#17900000
0"
#17950000
1"
#18000000
0"
b111100 $
b0 #
b0 &
#18050000
b0 !
b0 %
b0 '
1"
#18100000
0"
b100 #
b100 &
#18150000
b100 !
b100 %
b100 '
1"
#18200000
0"
#18250000
1"
#18300000
0"
b111101 $
b0 #
b0 &
#18350000
b0 !
b0 %
b0 '
1"
#18400000
0"
b100 #
b100 &
#18450000
b100 !
b100 %
b100 '
1"
#18500000
0"
#18550000
1"
#18600000
0"
b111110 $
b0 #
b0 &
#18650000
b0 !
b0 %
b0 '
1"
#18700000
0"
b100 #
b100 &
#18750000
b100 !
b100 %
b100 '
1"
#18800000
0"
#18850000
1"
#18900000
0"
b111111 $
b0 #
b0 &
#18950000
b0 !
b0 %
b0 '
1"
#19000000
0"
b100 #
b100 &
#19050000
b100 !
b100 %
b100 '
1"
#19100000
0"
#19150000
1"
#19200000
0"
b1000000 $
b0 #
b0 &
#19250000
b0 !
b0 %
b0 '
1"
#19300000
0"
b100 #
b100 &
#19350000
b100 !
b100 %
b100 '
1"
#19400000
0"
#19450000
1"
#19500000
0"
b1000001 $
b0 #
b0 &
#19550000
b0 !
b0 %
b0 '
1"
#19600000
0"
b100 #
b100 &
#19650000
b100 !
b100 %
b100 '
1"
#19700000
0"
#19750000
1"
#19800000
0"
b1000010 $
b0 #
b0 &
#19850000
b0 !
b0 %
b0 '
1"
#19900000
0"
b100 #
b100 &
#19950000
b100 !
b100 %
b100 '
1"
#20000000
0"
#20050000
1"
#20100000
0"
b1000011 $
b0 #
b0 &
#20150000
b0 !
b0 %
b0 '
1"
#20200000
0"
b100 #
b100 &
#20250000
b100 !
b100 %
b100 '
1"
#20300000
0"
#20350000
1"
#20400000
0"
b1000100 $
b0 #
b0 &
#20450000
b0 !
b0 %
b0 '
1"
#20500000
0"
b100 #
b100 &
#20550000
b100 !
b100 %
b100 '
1"
#20600000
0"
#20650000
1"
#20700000
0"
b1000101 $
b0 #
b0 &
#20750000
b0 !
b0 %
b0 '
1"
#20800000
0"
b100 #
b100 &
#20850000
b100 !
b100 %
b100 '
1"
#20900000
0"
#20950000
1"
#21000000
0"
b1000110 $
b0 #
b0 &
#21050000
b0 !
b0 %
b0 '
1"
#21100000
0"
b100 #
b100 &
#21150000
b100 !
b100 %
b100 '
1"
#21200000
0"
#21250000
1"
#21300000
0"
b1000111 $
b0 #
b0 &
#21350000
b0 !
b0 %
b0 '
1"
#21400000
0"
b100 #
b100 &
#21450000
b100 !
b100 %
b100 '
1"
#21500000
0"
#21550000
1"
#21600000
0"
b1001000 $
b0 #
b0 &
#21650000
b0 !
b0 %
b0 '
1"
#21700000
0"
b100 #
b100 &
#21750000
b100 !
b100 %
b100 '
1"
#21800000
0"
#21850000
1"
#21900000
0"
b1001001 $
b0 #
b0 &
#21950000
b0 !
b0 %
b0 '
1"
#22000000
0"
b100 #
b100 &
#22050000
b100 !
b100 %
b100 '
1"
#22100000
0"
#22150000
1"
#22200000
0"
b1001010 $
b0 #
b0 &
#22250000
b0 !
b0 %
b0 '
1"
#22300000
0"
b100 #
b100 &
#22350000
b100 !
b100 %
b100 '
1"
#22400000
0"
#22450000
1"
#22500000
0"
b1001011 $
b0 #
b0 &
#22550000
b0 !
b0 %
b0 '
1"
#22600000
0"
b100 #
b100 &
#22650000
b100 !
b100 %
b100 '
1"
#22700000
0"
#22750000
1"
#22800000
0"
b1001100 $
b0 #
b0 &
#22850000
b0 !
b0 %
b0 '
1"
#22900000
0"
b100 #
b100 &
#22950000
b100 !
b100 %
b100 '
1"
#23000000
0"
#23050000
1"
#23100000
0"
b1001101 $
b0 #
b0 &
#23150000
b0 !
b0 %
b0 '
1"
#23200000
0"
b100 #
b100 &
#23250000
b100 !
b100 %
b100 '
1"
#23300000
0"
#23350000
1"
#23400000
0"
b1001110 $
b0 #
b0 &
#23450000
b0 !
b0 %
b0 '
1"
#23500000
0"
b100 #
b100 &
#23550000
b100 !
b100 %
b100 '
1"
#23600000
0"
#23650000
1"
#23700000
0"
b1001111 $
b0 #
b0 &
#23750000
b0 !
b0 %
b0 '
1"
#23800000
0"
b100 #
b100 &
#23850000
b100 !
b100 %
b100 '
1"
#23900000
0"
#23950000
1"
#24000000
0"
b1010000 $
b0 #
b0 &
#24050000
b0 !
b0 %
b0 '
1"
#24100000
0"
b100 #
b100 &
#24150000
b100 !
b100 %
b100 '
1"
#24200000
0"
#24250000
1"
#24300000
0"
b1010001 $
b0 #
b0 &
#24350000
b0 !
b0 %
b0 '
1"
#24400000
0"
b100 #
b100 &
#24450000
b100 !
b100 %
b100 '
1"
#24500000
0"
#24550000
1"
#24600000
0"
b1010010 $
b0 #
b0 &
#24650000
b0 !
b0 %
b0 '
1"
#24700000
0"
b100 #
b100 &
#24750000
b100 !
b100 %
b100 '
1"
#24800000
0"
#24850000
1"
#24900000
0"
b1010011 $
b0 #
b0 &
#24950000
b0 !
b0 %
b0 '
1"
#25000000
0"
b100 #
b100 &
#25050000
b100 !
b100 %
b100 '
1"
#25100000
0"
#25150000
1"
#25200000
0"
b1010100 $
b0 #
b0 &
#25250000
b0 !
b0 %
b0 '
1"
#25300000
0"
b100 #
b100 &
#25350000
b100 !
b100 %
b100 '
1"
#25400000
0"
#25450000
1"
#25500000
0"
b1010101 $
b0 #
b0 &
#25550000
b0 !
b0 %
b0 '
1"
#25600000
0"
b100 #
b100 &
#25650000
b100 !
b100 %
b100 '
1"
#25700000
0"
#25750000
1"
#25800000
0"
b1010110 $
b0 #
b0 &
#25850000
b0 !
b0 %
b0 '
1"
#25900000
0"
b100 #
b100 &
#25950000
b100 !
b100 %
b100 '
1"
#26000000
0"
#26050000
1"
#26100000
0"
b1010111 $
b0 #
b0 &
#26150000
b0 !
b0 %
b0 '
1"
#26200000
0"
b100 #
b100 &
#26250000
b100 !
b100 %
b100 '
1"
#26300000
0"
#26350000
1"
#26400000
0"
b1011000 $
b0 #
b0 &
#26450000
b0 !
b0 %
b0 '
1"
#26500000
0"
b100 #
b100 &
#26550000
b100 !
b100 %
b100 '
1"
#26600000
0"
#26650000
1"
#26700000
0"
b1011001 $
b0 #
b0 &
#26750000
b0 !
b0 %
b0 '
1"
#26800000
0"
b100 #
b100 &
#26850000
b100 !
b100 %
b100 '
1"
#26900000
0"
#26950000
1"
#27000000
0"
b1011010 $
b0 #
b0 &
#27050000
b0 !
b0 %
b0 '
1"
#27100000
0"
b100 #
b100 &
#27150000
b100 !
b100 %
b100 '
1"
#27200000
0"
#27250000
1"
#27300000
0"
b1011011 $
b0 #
b0 &
#27350000
b0 !
b0 %
b0 '
1"
#27400000
0"
b100 #
b100 &
#27450000
b100 !
b100 %
b100 '
1"
#27500000
0"
#27550000
1"
#27600000
0"
b1011100 $
b0 #
b0 &
#27650000
b0 !
b0 %
b0 '
1"
#27700000
0"
b100 #
b100 &
#27750000
b100 !
b100 %
b100 '
1"
#27800000
0"
#27850000
1"
#27900000
0"
b1011101 $
b0 #
b0 &
#27950000
b0 !
b0 %
b0 '
1"
#28000000
0"
b100 #
b100 &
#28050000
b100 !
b100 %
b100 '
1"
#28100000
0"
#28150000
1"
#28200000
0"
b1011110 $
b0 #
b0 &
#28250000
b0 !
b0 %
b0 '
1"
#28300000
0"
b100 #
b100 &
#28350000
b100 !
b100 %
b100 '
1"
#28400000
0"
#28450000
1"
#28500000
0"
b1011111 $
b0 #
b0 &
#28550000
b0 !
b0 %
b0 '
1"
#28600000
0"
b100 #
b100 &
#28650000
b100 !
b100 %
b100 '
1"
#28700000
0"
#28750000
1"
#28800000
0"
b1100000 $
b0 #
b0 &
#28850000
b0 !
b0 %
b0 '
1"
#28900000
0"
b100 #
b100 &
#28950000
b100 !
b100 %
b100 '
1"
#29000000
0"
#29050000
1"
#29100000
0"
b1100001 $
b0 #
b0 &
#29150000
b0 !
b0 %
b0 '
1"
#29200000
0"
b100 #
b100 &
#29250000
b100 !
b100 %
b100 '
1"
#29300000
0"
#29350000
1"
#29400000
0"
b1100010 $
b0 #
b0 &
#29450000
b0 !
b0 %
b0 '
1"
#29500000
0"
b100 #
b100 &
#29550000
b100 !
b100 %
b100 '
1"
#29600000
0"
#29650000
1"
#29700000
0"
b1100011 $
b0 #
b0 &
#29750000
b0 !
b0 %
b0 '
1"
#29800000
0"
b100 #
b100 &
#29850000
b100 !
b100 %
b100 '
1"
#29900000
0"
#29950000
1"
#30000000
0"
b1100100 $
b1000 #
b1000 &
#30050000
b1000 !
b1000 %
b1000 '
1"
